[
    {
        "ctx": "Janša: Z Drnovškom sva razčistila nesporazum",
        "ctx_link": "https://www.finance.si/finance/jansa-z-drnovskom-sva-razcistila-nesporazum/a/164147",
        "upvotes": 0,
        "content": "\nBravo JJ. Treba je bilo prenehati in se z \"omračenim\", kot ga nekdo\nimenuje, pogovoriti.\nSeveda ni bilo pričakovati, da bi neplodno in tudi dobremu imenu\nškodljivo prekinitev nesodelovanja, kdo opazil pred 24 urami.",
        "author": "anon-76481"
    },
    {
        "ctx": "Janša: Z Drnovškom sva razčistila nesporazum",
        "ctx_link": "https://www.finance.si/finance/jansa-z-drnovskom-sva-razcistila-nesporazum/a/164147",
        "upvotes": 0,
        "content": "\nNe bi verjel, da lahko tudi popuši. kdo?",
        "author": "anon-86275"
    }
]