[
    {
        "ctx": "Dan varčevanja: Lani smo privarčevali kar 23 odstotkov razpoložljivega dohodka",
        "ctx_link": "https://live.finance.si/dan-varcevanja-lani-smo-privarcevali-kar-23-odstotkov-razpolozljivega-dohodka/a/8981713",
        "upvotes": 1,
        "content": "\nMi pa zapravili 300 procentov,kdo je boljši pri dnašnji inflaciji ?",
        "author": "FIN-467473"
    },
    {
        "ctx": "Dan varčevanja: Lani smo privarčevali kar 23 odstotkov razpoložljivega dohodka",
        "ctx_link": "https://live.finance.si/dan-varcevanja-lani-smo-privarcevali-kar-23-odstotkov-razpolozljivega-dohodka/a/8981713",
        "upvotes": 0,
        "content": "\nOSEBNE FINANCE V SLOVENIJI\n\n* Depoziti v bankah - 39,8% = 26.900 €\n* Gotovina - 8,2% = 5.700 €\n* Življenjska in pokojninska zavarovanja - 14% = 9.700 €\n* Lastniški kapital - 30% = 20.600 €\n* Drugo - 8% = 5.500 €\n\nwww.zps.si/index.php...ne-finance\n\nbb.si/f/docs/diploms...enka_1.pdf\n\n\nvsebovredu.triglav.s...ate-narobe\nwww.delavska-hraniln...ne-finance\n\n\ndk.um.si/IzpisGradiv...9584203:d3\nwww.nlb.si/5-korakov...nih-financ\n\nwww.nlb.si/ocena-poz...nih-financ\n\n\nwww.finance.si/89649...nih-financ\n\nsvetkapitala.delo.si...a-razgali/\n\nwww.academia.si/wp-c...gorsek.pdf\n\nwww.mojaobcina.si/gr...lubej.html\nwww.financna-sola.si...amo-lubej/\n\nwww.financna-sola.si/\n\nmojefinance.finance....z-denarjem\n\nwww.cresus.si/wp-con...7-2014.pdf\n\nwww.zivljenje55plus....financami/\n\nwww.zlus.si/wp-conte...inance.pdf\n\nwww.mestomladih.si/s...ljiv-cilj/\nsi.linkedin.com/in/s...c-2b9890ab\n\n\nwww.vezovisek.si/wp-...inance.pdf\nwww.dnevnik.si/1042769482\n\nwww.zurnal24.si/slov...inah-33047\n\n\nwww.individa-partner...kcij_2.pdf\nwww.cek.ef.uni-lj.si...ric720.pdf\n\n\nconsult.vzajemci.com...gKthvD_BwE\ncore.ac.uk/download/...526041.pdf\n\nwww.prirocnikporoka....ih-financ/",
        "author": "zoran13"
    }
]