[
    {
        "ctx": "Prevcu do brona zmanjkalo pol točke",
        "ctx_link": "https://live.finance.si/prevcu-do-brona-zmanjkalo-pol-tocke/a/8986010",
        "upvotes": 3,
        "content": "\nOdlična uvrstitev. Le tiste nagrade ne bo, ampak ni vse v denarju.\nGlavo pokonci, jutri je nova tekma. Lep dan.",
        "author": "bigl"
    },
    {
        "ctx": "Prevcu do brona zmanjkalo pol točke",
        "ctx_link": "https://live.finance.si/prevcu-do-brona-zmanjkalo-pol-tocke/a/8986010",
        "upvotes": 1,
        "content": "\nZadnja sprememba: najobj 06.02.2022 14:48\n... Prevcu do brona zmanjkalo pol točke ...\n\n... eh, tako blizu, pa tako daleč ...\n\nP.S.: popravite rezultate v en sam stavek dolgem \"članku\" ali pa\nnapišite, da ste objavili rezultate po prvi seriji, ker namreč na\nkoncu je bil Timi Zajc deveti, Anže Lanišek trinajsti, Lovro Kos pa\nje tudi na koncu ostal osemindvajseti ...",
        "author": "najobj"
    }
]