[
    {
        "ctx": "Silvo Plut s prerezanimi zapestji v Kliničnem centru",
        "ctx_link": "https://www.finance.si/finance/silvo-plut-s-prerezanimi-zapestji-v-klinicnem-centru/a/165240",
        "upvotes": 0,
        "content": "\nBogi Plut, še umreti mu ne pustijo.",
        "author": "anon-1670"
    },
    {
        "ctx": "Silvo Plut s prerezanimi zapestji v Kliničnem centru",
        "ctx_link": "https://www.finance.si/finance/silvo-plut-s-prerezanimi-zapestji-v-klinicnem-centru/a/165240",
        "upvotes": 0,
        "content": "\nŠe par ur, pa ga bo spet cela Slovenija iskala, se bojim...",
        "author": "anon-15393"
    }
]