[
  {
    "ctx": "Vlada je regulirala ceno daljinskega ogrevanja za 130 tisoč gospodinjstev",
    "ctx_link": "https://live.finance.si/vlada-je-regulirala-ceno-daljinskega-ogrevanja-za-130-tisoc-gospodinjstev/a/9005452",
    "upvotes": 0,
    "content": "\nNa netu je cenik toplote komunale Trbovlje, kjer piše variabilni\ndel 220 EUR na MWh. Pa kdo je tu nor? Z električno pečjo bo ceneje.\nNaj dovoloijo vsem prosto izbiro ogrevanja, tudi odklop od sistema.",
    "author": "MF-382439"
  },
  {
    "ctx": "Vlada je regulirala ceno daljinskega ogrevanja za 130 tisoč gospodinjstev",
    "ctx_link": "https://live.finance.si/vlada-je-regulirala-ceno-daljinskega-ogrevanja-za-130-tisoc-gospodinjstev/a/9005452",
    "upvotes": 0,
    "content": "\nNa netu je cenik toplote komunale Trbovlje, kjer piše variabilni\ndel 220 EUR na MWh. Pa kdo je tu nor? Z električno pečjo bo ceneje.\nNaj dovoloijo vsem prosto izbiro ogrevanja, tudi odklop od sistema.",
    "author": "MF-382439"
  }
]