[
    {
        "ctx": "Prihodnost brez monitorjev?",
        "ctx_link": "https://www.finance.si/manager/prihodnost-brez-monitorjev/a/9005009",
        "upvotes": 2,
        "content": "\nverjemi, da je to prihodnost, samo vprašanje časa",
        "author": "najed79"
    },
    {
        "ctx": "Prihodnost brez monitorjev?",
        "ctx_link": "https://www.finance.si/manager/prihodnost-brez-monitorjev/a/9005009",
        "upvotes": 1,
        "content": "\nTole poriva Meta? Hm...",
        "author": "Froc"
    },
    {
        "ctx": "Prihodnost brez monitorjev?",
        "ctx_link": "https://www.finance.si/manager/prihodnost-brez-monitorjev/a/9005009",
        "upvotes": 1,
        "content": "\nSe strinjam, ni šans. LP\nKot pravi John Oliver (0:00-0:48:\nwww.youtube.com/watc...6iDZspbRMg",
        "author": "Rokc5"
    },
    {
        "ctx": "Prihodnost brez monitorjev?",
        "ctx_link": "https://www.finance.si/manager/prihodnost-brez-monitorjev/a/9005009",
        "upvotes": 4,
        "content": "\nZadnja sprememba: ogo 21.10.2022 16:26\n[Froc]\nTole poriva Meta? Hm...\nApfl Štrudl Corporation bo pa naslednje leto.\niOčale za 3999,99 EUR osnovni model. iOčale Pro Max pa za 9999,99\nEUR. :P",
        "author": "ogo"
    },
    {
        "ctx": "Prihodnost brez monitorjev?",
        "ctx_link": "https://www.finance.si/manager/prihodnost-brez-monitorjev/a/9005009",
        "upvotes": 2,
        "content": "\nPa pašček, s katerim si to na glavo natakneš bo 99,99 USD. Se\nprodaja posebej.",
        "author": "Endimion"
    }
]