[
    {
        "ctx": "Novinec med milijonarji: Z blockchain rešitvijo do pogodbe z egiptovsko vlado ",
        "ctx_link": "https://www.finance.si/najbogatejsi-slovenci/novinec-med-milijonarji-z-blockchain-resitvijo-do-pogodbe-z-egiptovsko-vlado/a/9005987",
        "upvotes": 0,
        "content": "\nBravo!\nTakole od daleč je videti, da so dolgo garali za dober izdelek in\nnjegovo uveljavitev.\nNa koncu so verjetno naredili preboj s pomočjo partnerja, ki\nobvlada specifične poslovne prakse držav, kot je Egipt.",
        "author": "FjodorKirilovic"
    }
]