[
    {
        "ctx": "Val likvidacij biankoček podjetij",
        "ctx_link": "https://live.finance.si/val-likvidacij-biankocek-podjetij/a/9007233",
        "upvotes": 0,
        "content": "\nSPAC (Special Purpose Acquisition Company) je družba, ki nima\nnobenega poslovnega modela. Ustanovitelji jo oblikujejo izključno\nza vstop na borzo. Po uspešnem začetku kotacije vodilni zbrana\nsredstva naložijo v varne vrednostne papirje, kot so kratkoročni\ndepoziti, in nato čakajo na primerno podjetje, da ga prevzamejo in\nmu tako olajšajo vstop na borzo. Ob vstopu na borzo kupci delnic\nbiankoček podjetja ne vedo, koga namerava vodstvo prevzeti.\nVečinoma morajo prevzemno tarčo najti v prvih dveh letih po vstopu\nna borzo. V nasprotnem primeru morajo vlagateljem denar\nvrniti.\n\nSouth Sea Bubble of 1720? :)",
        "author": "Endimion"
    },
    {
        "ctx": "Val likvidacij biankoček podjetij",
        "ctx_link": "https://live.finance.si/val-likvidacij-biankocek-podjetij/a/9007233",
        "upvotes": 0,
        "content": "\nDaleč od tega, bolj za razvezo depozita in vračilo denarja.",
        "author": "hostamox"
    },
    {
        "ctx": "Val likvidacij biankoček podjetij",
        "ctx_link": "https://live.finance.si/val-likvidacij-biankocek-podjetij/a/9007233",
        "upvotes": 1,
        "content": "\nČe ga je kaj... :)",
        "author": "Endimion"
    }
]