[
    {
        "ctx": "V Italiji industrijska proizvodnja medletno upadla za 7,2 odstotka",
        "ctx_link": "https://live.finance.si/v-italiji-industrijska-proizvodnja-medletno-upadla-za-72-odstotka/a/9014004",
        "upvotes": 5,
        "content": "\nOhlajanje gospodarstva je očitna posledica let debelih krav... in\nvsega natiskanega denarja, s katerim so zalivali ljudi in\ngospodarstvo. Sedaj pa je prišla inflacija, rast stroškov\n(surovin), tiska se manj, zaliva se manj, kreditov ni, ker so\nobrestne mere izjemno visoke...\n... logično, sledi recesija. Najprej v proizvodnji, nato v\nstoritvah... vsi bodo previdni. Državne blagajne pa zadolžene,\nkoliko imajo manevrskega prostora, kdo ve. Gledamo USA, kako gredo\nproti 130% ali več javnemu primanjkljaju, pa nikome ništa. Če lahko\noni, lahko tudi ostali...\n... vse skupaj je farsa z vidika resne ekonomije.",
        "author": "FIN-379669"
    }
]