[
  {
    "ctx": "Patagonia: Kako se podjetje iz umazane industrije hoče očistiti",
    "ctx_link": "https://www.finance.si/manager/patagonia-kako-se-podjetje-iz-umazane-industrije-hoce-ocistiti/a/9015353",
    "upvotes": 0,
    "content": "\nPriporočam v branje V Patagoniji Bruca Chatwina, najboljšega\npotopisca. Nihče je ni bolje opisal. Lep dan.",
    "author": "bigl"
  },
  {
    "ctx": "Patagonia: Kako se podjetje iz umazane industrije hoče očistiti",
    "ctx_link": "https://www.finance.si/manager/patagonia-kako-se-podjetje-iz-umazane-industrije-hoce-ocistiti/a/9015353",
    "upvotes": 0,
    "content": "\nEno samo zavajanje turbo kapitalistov.\n\nMoralno sporno je tudi ime, da kapitalist s tem v podzavesti vpliva\nna kupce, ker imajo o tapravi Patagoniji prelepe slike v\nspominu.\n\nKo slišiš za Patagonijo takoj pomisliš na enkratno in čudovito\npokrajino.\n\nZa tega izkoriščevalca delavcev pa sedaj slišim prvič.",
    "author": "FIN-544124"
  },
  {
    "ctx": "Patagonia: Kako se podjetje iz umazane industrije hoče očistiti",
    "ctx_link": "https://www.finance.si/manager/patagonia-kako-se-podjetje-iz-umazane-industrije-hoce-ocistiti/a/9015353",
    "upvotes": 0,
    "content": "\nPriporočam v branje V Patagoniji Bruca Chatwina, najboljšega\npotopisca. Nihče je ni bolje opisal. Lep dan.",
    "author": "bigl"
  },
  {
    "ctx": "Patagonia: Kako se podjetje iz umazane industrije hoče očistiti",
    "ctx_link": "https://www.finance.si/manager/patagonia-kako-se-podjetje-iz-umazane-industrije-hoce-ocistiti/a/9015353",
    "upvotes": 0,
    "content": "\nEno samo zavajanje turbo kapitalistov.\n\nMoralno sporno je tudi ime, da kapitalist s tem v podzavesti vpliva\nna kupce, ker imajo o tapravi Patagoniji prelepe slike v\nspominu.\n\nKo slišiš za Patagonijo takoj pomisliš na enkratno in čudovito\npokrajino.\n\nZa tega izkoriščevalca delavcev pa sedaj slišim prvič.",
    "author": "FIN-544124"
  }
]