[
  {
    "ctx": "DZ potrdil interventni zakon za pomoč po poplavah ",
    "ctx_link": "https://live.finance.si/dz-potrdil-interventni-zakon-za-pomoc-po-poplavah/a/9016343",
    "upvotes": 6,
    "content": "\nŠe podržavimo podjetja zaradi krize države, zaplenimo ljudem\nprihranke in smo popolni.",
    "author": "slovenecnb1"
  },
  {
    "ctx": "DZ potrdil interventni zakon za pomoč po poplavah ",
    "ctx_link": "https://live.finance.si/dz-potrdil-interventni-zakon-za-pomoc-po-poplavah/a/9016343",
    "upvotes": 6,
    "content": "\nŠe podržavimo podjetja zaradi krize države, zaplenimo ljudem\nprihranke in smo popolni.",
    "author": "slovenecnb1"
  }
]