[
  {
    "ctx": "Rezultati Save Re: dobiček bo kljub poplavam blizu načrtom",
    "ctx_link": "https://live.finance.si/rezultati-save-re-dobicek-bo-kljub-poplavam-blizu-nacrtom/a/9018737",
    "upvotes": 3,
    "content": "\nBravo Sava Re.",
    "author": "EKSPROPRIACIJA"
  },
  {
    "ctx": "Rezultati Save Re: dobiček bo kljub poplavam blizu načrtom",
    "ctx_link": "https://live.finance.si/rezultati-save-re-dobicek-bo-kljub-poplavam-blizu-nacrtom/a/9018737",
    "upvotes": 0,
    "content": "\nZadnja sprememba: murje 17.11.2023 14:24\nDIVIDENDA\n\nUravnotežen dobiček in stabilne dividende\nPortfelj skupine je dobro uravnotežen glede na zastopanost zgodnje-\nin poznocikličnih panog, kar zagotavlja tudi stabilno\ndobičkonosnost kapitala skupine in rast dividende na delnico.\nwww.sava-re.si/sl-si...lagatelje/\n\n\n* Cena delnice na borzi:\n* 08.11.2008 - 28,12 €\n* 28.11.2011 - 5,15 €\n* 08.02.2012 - 4,60 €\n* 24.07.2012 - 4,51 € - min\n* 13.06.2013 - 7,00 € - (II. javna prodaja IPO)\n* 29.05.2018 - 19,00 €\n* 12.02.2020 - 20,60 €\n* 23.03.2020 - 13,40 €\n* 28.08.2020 - 17,20 €\n* 08.09.2020 - 16,40 €\n* 12.01.2021 - 19,90 €\n* 03.02.2021 - 20,60 €\n* 04.02.2021 - 21,20 €\n* 01.03.2021 - 23,40 €\n* 07.05.2021 - 23,00 €\n* 03.06.2021 - 26,90 €\n* 30.07.2021 - 27,50 €\n* 02.08.2021 - 28,00 €\n* 17.08.2021 - 28,30 €\n* 18.08.2021 - 29,10 €\n* 24.11.2021 - 29,80 €\n* 14.01.2022 - 29,60 €\n* 20.01.2022 - 30,40 € - max.\n* 24.06.2022 - 25,20 €\n* 17.11.2023 - 23,70 €\n\n* Dividenda:\n* 2013 - 0,26 €\n* 2014 - 0,55 €\n* 2015 - 0,80 €\n* 2016 - 0,80 €\n* 2017 - 0,80 €\n* 2018 - 0,95 €\n* 2019 - 0 €\n* 2020 - 0,85 €\n* 2021 - 1,50 €\n* 2022 - 1,60 € - maksimalna izplačana dividenda\n* 2023 - ? €\n\nBomo videli, kako bo v naslednjem letu...\nwww.sava-re.si/sl-si...lagatelje/\n\n\nDOKAPITALIZACIJe\n\nZadnjič je direktorica Slovenskega zavarovalniškega združenja maja\nKrumberger, ob problematiki izplačevanja odškodnih zaradi poplav,\npovedala, da so zavarovalnice organizirane, kot delniške družbe in\nbi se v primeru izgube, morale dokapitalizirati\".\nwww.zav-zdruzenje.si/\nwww.zav-zdruzenje.si...iziranost/",
    "author": "murje"
  },
  {
    "ctx": "Rezultati Save Re: dobiček bo kljub poplavam blizu načrtom",
    "ctx_link": "https://live.finance.si/rezultati-save-re-dobicek-bo-kljub-poplavam-blizu-nacrtom/a/9018737",
    "upvotes": 3,
    "content": "\nBravo Sava Re.",
    "author": "EKSPROPRIACIJA"
  },
  {
    "ctx": "Rezultati Save Re: dobiček bo kljub poplavam blizu načrtom",
    "ctx_link": "https://live.finance.si/rezultati-save-re-dobicek-bo-kljub-poplavam-blizu-nacrtom/a/9018737",
    "upvotes": 0,
    "content": "\nZadnja sprememba: murje 17.11.2023 14:24\nDIVIDENDA\n\nUravnotežen dobiček in stabilne dividende\nPortfelj skupine je dobro uravnotežen glede na zastopanost zgodnje-\nin poznocikličnih panog, kar zagotavlja tudi stabilno\ndobičkonosnost kapitala skupine in rast dividende na delnico.\nwww.sava-re.si/sl-si...lagatelje/\n\n\n* Cena delnice na borzi:\n* 08.11.2008 - 28,12 €\n* 28.11.2011 - 5,15 €\n* 08.02.2012 - 4,60 €\n* 24.07.2012 - 4,51 € - min\n* 13.06.2013 - 7,00 € - (II. javna prodaja IPO)\n* 29.05.2018 - 19,00 €\n* 12.02.2020 - 20,60 €\n* 23.03.2020 - 13,40 €\n* 28.08.2020 - 17,20 €\n* 08.09.2020 - 16,40 €\n* 12.01.2021 - 19,90 €\n* 03.02.2021 - 20,60 €\n* 04.02.2021 - 21,20 €\n* 01.03.2021 - 23,40 €\n* 07.05.2021 - 23,00 €\n* 03.06.2021 - 26,90 €\n* 30.07.2021 - 27,50 €\n* 02.08.2021 - 28,00 €\n* 17.08.2021 - 28,30 €\n* 18.08.2021 - 29,10 €\n* 24.11.2021 - 29,80 €\n* 14.01.2022 - 29,60 €\n* 20.01.2022 - 30,40 € - max.\n* 24.06.2022 - 25,20 €\n* 17.11.2023 - 23,70 €\n\n* Dividenda:\n* 2013 - 0,26 €\n* 2014 - 0,55 €\n* 2015 - 0,80 €\n* 2016 - 0,80 €\n* 2017 - 0,80 €\n* 2018 - 0,95 €\n* 2019 - 0 €\n* 2020 - 0,85 €\n* 2021 - 1,50 €\n* 2022 - 1,60 € - maksimalna izplačana dividenda\n* 2023 - ? €\n\nBomo videli, kako bo v naslednjem letu...\nwww.sava-re.si/sl-si...lagatelje/\n\n\nDOKAPITALIZACIJe\n\nZadnjič je direktorica Slovenskega zavarovalniškega združenja maja\nKrumberger, ob problematiki izplačevanja odškodnih zaradi poplav,\npovedala, da so zavarovalnice organizirane, kot delniške družbe in\nbi se v primeru izgube, morale dokapitalizirati\".\nwww.zav-zdruzenje.si/\nwww.zav-zdruzenje.si...iziranost/",
    "author": "murje"
  }
]