[
  {
    "ctx": "Češki milijarder Kretinsky, polovični lastnik družbe SŽ - Tovorni promet, pred vstopom v Thyssenkrupp",
    "ctx_link": "https://www.finance.si/transport-logistika/ceski-milijarder-kretinsky-polovicni-lastnik-druzbe-sz-tovorni-promet-pred-vstopom-v-thyssenkrupp/a/9018914",
    "upvotes": 1,
    "content": "\nŽal je to nadaljevanje razprodaje slovenskega razumevanja\nnacionalnega interesa in ponosa...",
    "author": "murje"
  },
  {
    "ctx": "Češki milijarder Kretinsky, polovični lastnik družbe SŽ - Tovorni promet, pred vstopom v Thyssenkrupp",
    "ctx_link": "https://www.finance.si/transport-logistika/ceski-milijarder-kretinsky-polovicni-lastnik-druzbe-sz-tovorni-promet-pred-vstopom-v-thyssenkrupp/a/9018914",
    "upvotes": 1,
    "content": "\nŽal je to nadaljevanje razprodaje slovenskega razumevanja\nnacionalnega interesa in ponosa...",
    "author": "murje"
  }
]