[
  {
    "ctx": "Tesla je glavno gonilo vnovične rasti nemške avtoindustrije",
    "ctx_link": "https://www.finance.si/avto/tesla-je-glavno-gonilo-vnovicne-rasti-nemske-avtoindustrije/a/9020153",
    "upvotes": 5,
    "content": "\nPo stopnji rasti bo Nemčija\nprehitela Kitajsko\nTeden dni nazaj smo brali, kako so v recesiji.",
    "author": "FiskalnaFinta"
  },
  {
    "ctx": "Tesla je glavno gonilo vnovične rasti nemške avtoindustrije",
    "ctx_link": "https://www.finance.si/avto/tesla-je-glavno-gonilo-vnovicne-rasti-nemske-avtoindustrije/a/9020153",
    "upvotes": 1,
    "content": "\nTesla Berlin to suspend most production for two weeks over Red Sea\nsupply gap - \nwww.nasdaq.com/artic...supply-gap",
    "author": "crt"
  },
  {
    "ctx": "Tesla je glavno gonilo vnovične rasti nemške avtoindustrije",
    "ctx_link": "https://www.finance.si/avto/tesla-je-glavno-gonilo-vnovicne-rasti-nemske-avtoindustrije/a/9020153",
    "upvotes": 5,
    "content": "\nPo stopnji rasti bo Nemčija\nprehitela Kitajsko\nTeden dni nazaj smo brali, kako so v recesiji.",
    "author": "FiskalnaFinta"
  },
  {
    "ctx": "Tesla je glavno gonilo vnovične rasti nemške avtoindustrije",
    "ctx_link": "https://www.finance.si/avto/tesla-je-glavno-gonilo-vnovicne-rasti-nemske-avtoindustrije/a/9020153",
    "upvotes": 1,
    "content": "\nTesla Berlin to suspend most production for two weeks over Red Sea\nsupply gap - \nwww.nasdaq.com/artic...supply-gap",
    "author": "crt"
  }
]