[
    {
        "ctx": "Evropska komisija preverja ali Meta krši akt o digitalnih storitvah",
        "ctx_link": "https://live.finance.si/evropska-komisija-preverja-ali-meta-krsi-akt-o-digitalnih-storitvah/a/9023424",
        "upvotes": 1,
        "content": "\nTi eu bebci in tud naši bebci se res ne znajo ukvarjat kot z\nzamaški na flašah električnimi paneli ki so popolnoma neučinkoviti\nin s predpisi in to je eu blaginja pa res ni čudno da nas ima putin\nza tepce ko ma take sogovornike",
        "author": "slovenecnb1"
    },
    {
        "ctx": "Evropska komisija preverja ali Meta krši akt o digitalnih storitvah",
        "ctx_link": "https://live.finance.si/evropska-komisija-preverja-ali-meta-krsi-akt-o-digitalnih-storitvah/a/9023424",
        "upvotes": 0,
        "content": "\nNi samo v Meti (aka Facebook) problem. Problem je v vseh oblačnih\nponudnikih, ki bi jih morali končno zauzdati. Ker to kar se dogaja\nsedaj je divji zahod , v korist ponudnikov tovrstnih storitev :)",
        "author": "0531Zavar"
    }
]