[
    {
        "ctx": "Težave z erekcijo so pogoste",
        "ctx_link": "https://www.finance.si/finance/tezave-z-erekcijo-so-pogoste/a/166761",
        "upvotes": 0,
        "content": "\n\"Določeno stopnjo erektilne disfunkcije ima približno polovica\nmoških, starejših od 40 let, to je okrog 152 milijonov moških na\nsvetu\".\n\nHmmm....tale izračun je pa precej čuden?!\nČe je na svetu 6 milijard prebivalcev, in recimo od tega polovica\nmoških (Ok, par milijonov manj), me res zanima ali je torej od 3\nmilijard moških le 300 milijonov (10%) starejših od 40 let? To bi\npomenilo, da je danes med vsemi moškimi 90% mlajših od 40 let, 10%\npa starejših. Glede na stopnjo staranja predvsem zahodnih držav\nmočno dvomim...",
        "author": "anon-29373"
    },
    {
        "ctx": "Težave z erekcijo so pogoste",
        "ctx_link": "https://www.finance.si/finance/tezave-z-erekcijo-so-pogoste/a/166761",
        "upvotes": 0,
        "content": "\nMogoče so mišljeni spolno aktivni. Torej tisti, ki kljub težavam še\nposkušajo :)",
        "author": "Gustl"
    },
    {
        "ctx": "Težave z erekcijo so pogoste",
        "ctx_link": "https://www.finance.si/finance/tezave-z-erekcijo-so-pogoste/a/166761",
        "upvotes": 0,
        "content": "\nali se ostalim sploh lahko še reče moški :)",
        "author": "anon-36971"
    },
    {
        "ctx": "Težave z erekcijo so pogoste",
        "ctx_link": "https://www.finance.si/finance/tezave-z-erekcijo-so-pogoste/a/166761",
        "upvotes": 0,
        "content": "\n\n1tolar wrote:\nali se ostalim sploh lahko še reče moški :)\n \nTako je, treba je opletat do zadnjega, pa čeprav s \"polamekanim\".\n:))\nOtac",
        "author": "anon-86509"
    }
]