[
  {
    "ctx": "Microsoft: Windows Vista je nared",
    "ctx_link": "https://www.finance.si/finance/microsoft-windows-vista-je-nared/a/167652",
    "upvotes": 0,
    "content": "\n:...da je bila izvorna koda Viste posredovana v razmnoževanje v\nsredo zjutraj.\n\nIzvorna koda???",
    "author": "anon-79054"
  },
  {
    "ctx": "Microsoft: Windows Vista je nared",
    "ctx_link": "https://www.finance.si/finance/microsoft-windows-vista-je-nared/a/167652",
    "upvotes": 0,
    "content": "\nIzvorna koda ;)",
    "author": "anon-45498"
  },
  {
    "ctx": "Microsoft: Windows Vista je nared",
    "ctx_link": "https://www.finance.si/finance/microsoft-windows-vista-je-nared/a/167652",
    "upvotes": 0,
    "content": "\n:...da je bila izvorna koda Viste posredovana v razmnoževanje v\nsredo zjutraj.\n\nIzvorna koda???",
    "author": "anon-79054"
  },
  {
    "ctx": "Microsoft: Windows Vista je nared",
    "ctx_link": "https://www.finance.si/finance/microsoft-windows-vista-je-nared/a/167652",
    "upvotes": 0,
    "content": "\nIzvorna koda ;)",
    "author": "anon-45498"
  }
]