[
    {
        "ctx": "Drobniča bo nasledila Marjeta Cotman",
        "ctx_link": "https://www.finance.si/finance/drobnica-bo-nasledila-marjeta-cotman/a/170019",
        "upvotes": 0,
        "content": "\nGrozno. Spet ena nekompetentna...",
        "author": "anon-10267"
    },
    {
        "ctx": "Drobniča bo nasledila Marjeta Cotman",
        "ctx_link": "https://www.finance.si/finance/drobnica-bo-nasledila-marjeta-cotman/a/170019",
        "upvotes": 0,
        "content": "\nV torek se je včlanila v Partijo (N.Si) in tako izpolnila pogoje.\nZgodovina se ponavlja :(",
        "author": "philips"
    }
]