[
  {
    "ctx": "Finkova in Vild ambasadorja koncepta USP",
    "ctx_link": "https://www.finance.si/kariera/finkova-in-vild-ambasadorja-koncepta-usp/a/173460",
    "upvotes": 0,
    "content": "\nMislim, da ni odveč zapisati dosežke novih ambasodorjev v širjenju\nkoncepta učečega se podjetja.\nObema ambasadorjema iskrene čestitke.",
    "author": "anon-6677"
  },
  {
    "ctx": "Finkova in Vild ambasadorja koncepta USP",
    "ctx_link": "https://www.finance.si/kariera/finkova-in-vild-ambasadorja-koncepta-usp/a/173460",
    "upvotes": 0,
    "content": "\nMislim, da ni odveč zapisati dosežke novih ambasodorjev v širjenju\nkoncepta učečega se podjetja.\nObema ambasadorjema iskrene čestitke.",
    "author": "anon-6677"
  }
]