[
  {
    "ctx": "Kadrovski prepih",
    "ctx_link": "https://www.finance.si/kariera/kadrovski-prepih/a/175806",
    "upvotes": 0,
    "content": "\nČudno da nbi niti besede o kadrovskih prepihih v mestni upravi. Če\nbi bil tam Arhar, bi to bili cunamiji, nevihte, viharji, vesoljni\npotop....",
    "author": "anon-75458"
  },
  {
    "ctx": "Kadrovski prepih",
    "ctx_link": "https://www.finance.si/kariera/kadrovski-prepih/a/175806",
    "upvotes": 0,
    "content": "\nČudno da nbi niti besede o kadrovskih prepihih v mestni upravi. Če\nbi bil tam Arhar, bi to bili cunamiji, nevihte, viharji, vesoljni\npotop....",
    "author": "anon-75458"
  }
]