[
    {
        "ctx": "Drnovšek še brez predloga za guvernerja",
        "ctx_link": "https://www.finance.si/finance/drnovsek-se-brez-predloga-za-guvernerja/a/179854",
        "upvotes": 0,
        "content": "\nSe mu je solata zataknila v grlu?",
        "author": "anon-3891"
    },
    {
        "ctx": "Drnovšek še brez predloga za guvernerja",
        "ctx_link": "https://www.finance.si/finance/drnovsek-se-brez-predloga-za-guvernerja/a/179854",
        "upvotes": 0,
        "content": "\n\nXBOGA1 je\nnapisal(a):\nSe mu je solata zataknila v grlu?\n \nEminentna domislica.",
        "author": "anon-4731"
    },
    {
        "ctx": "Drnovšek še brez predloga za guvernerja",
        "ctx_link": "https://www.finance.si/finance/drnovsek-se-brez-predloga-za-guvernerja/a/179854",
        "upvotes": 0,
        "content": "\n\nXBOGA1 je\nnapisal(a):\nSe mu je solata zataknila v grlu?\n\nne, dobil je zeleno drisko :)",
        "author": "RTM"
    }
]