[
    {
        "ctx": "Popravek: NS Term Čatež o nagradah",
        "ctx_link": "https://www.finance.si/finance/popravek-ns-term-catez-o-nagradah/a/180842",
        "upvotes": 0,
        "content": "\nŠportni objekti v samih termah so zelo zanemarjeni, zato bi nagrado\nlaho bolj godpodarno uporabili. Polomljeni so goli na nogometnem\nigrišču, koši so brez mrežic, v gnili košarkarski tabli tik pod\nobročem gnezdijo ptice. Zelo slabo so vzdrževana tudi teniška\nigrišča. P.S. Nek ljubitelj košarke je kupil mrežice in jih\nmontiral na koše, vse ostalo pa je zelo zelo slabo. Lep\npozdrav, Mare",
        "author": "anon-52559"
    }
]