[
    {
        "ctx": "Bivša direktorja Sove osumljena utaje davkov",
        "ctx_link": "https://www.finance.si/finance/bivsa-direktorja-sove-osumljena-utaje-davkov/a/182585",
        "upvotes": 0,
        "content": "\nSOVA uka, čuk jo f**a, to je po slovenskoooo... :)",
        "author": "anon-45881"
    },
    {
        "ctx": "Bivša direktorja Sove osumljena utaje davkov",
        "ctx_link": "https://www.finance.si/finance/bivsa-direktorja-sove-osumljena-utaje-davkov/a/182585",
        "upvotes": 0,
        "content": "\nSej ne morem verjet, huje kot otroci v peskovniku.",
        "author": "anon-48472"
    },
    {
        "ctx": "Bivša direktorja Sove osumljena utaje davkov",
        "ctx_link": "https://www.finance.si/finance/bivsa-direktorja-sove-osumljena-utaje-davkov/a/182585",
        "upvotes": 0,
        "content": "\nIn kako je avtor prišel do zneska višine davčne utaje \"okoli 10\ntisoč evrov\", če je bilo izplačanih \"dobrih 126 tisoč evrov\"?\nKako je lahko davčna utaja, če gre za črni fond, ki je nezakonit že\nsam po sebi; torej je višina davčne utaje lahko kvečjemu enaka\nvišini izplačil, a ne?",
        "author": "anon-76887"
    },
    {
        "ctx": "Bivša direktorja Sove osumljena utaje davkov",
        "ctx_link": "https://www.finance.si/finance/bivsa-direktorja-sove-osumljena-utaje-davkov/a/182585",
        "upvotes": 0,
        "content": "\nSova s kontinuiteto je država v državi!",
        "author": "anon-72895"
    }
]