[
  {
    "ctx": "Htc desire in iGO myWay",
    "content": "Torej na desira sem naložil iGo MyWay in nato kopiral karte \"IGO 8 maps East Europe 03-2010 by TopMap\" v mapo iGO. Sam program in navigacija po Sloveniji deluje super (sicer sprobano samo v LJ zaenkrat), problem pa je ker ne morem izbrati ostalih držav, ki naj bi bile v tem folderju. Edina država, ki jo lahko izberem pri iskanju je Slovenija. Ima kdo idejo zakaj je tako, oziroma ali obstaja kakšna rešitev?",
    "author": "LooK",
    "author_level": "Pripravnik"
  },
  {
    "ctx": "Htc desire in iGO myWay",
    "content": "Mogoče je kaj narobe z licenco?\nPraviš da ostale države NAJ bi bile v tem folderju? Pa so res tam?\nV mapci pusti Slovenijo, ter testiraj recimo z Avstrijo ...",
    "author": "Bucko",
    "author_level": "Fizikalc"
  }
]