[
  {
    "ctx": "P:Kupon za brezplačno priključnino Tušmobil",
    "content": "Pozdravljeni,\n\nOb predložitvi kupončka in sklenitvi aneksa (nakup tel. aparata ali popusta na naročnino) se vam ne zaračuna priključnina v vrednosti 10, 00 EUR, tudi ne za dodatne številke, s katerimi sklenete aneks pri paketih Brezmejni. Kupon vam pošljem brezplačno na lastne stroške.\n\nOb sklenitvi naročniškega razmerja si lahko izberete še odličen telefon, že od 1 evra naprej ( Nokia N8, Samsung Galaxy, LG Optimus; HTC Desire ipd).\n\nPridružite se že 220. 000 uporabnikom Tušmobila!\n\nKupone pošljem v roku enega dneva, za vse dodatne informacije pa se lahko obrnete na elektronsko pošto. \n\nZa vse dodatne informacije pa na ZS ali na tadej .ropret @gmail.com",
    "author": "tado",
    "author_level": "Fizikalc"
  },
  {
    "ctx": "P:Kupon za brezplačno priključnino Tušmobil",
    "content": "Še je na voljo?",
    "author": "malcomX",
    "author_level": "Plastic"
  },
  {
    "ctx": "P:Kupon za brezplačno priključnino Tušmobil",
    "content": "Še na voljo. Prosim za podatke na ZS.",
    "author": "tado",
    "author_level": "Fizikalc"
  },
  {
    "ctx": "P:Kupon za brezplačno priključnino Tušmobil",
    "content": "zdaj sm pa že sklenil naročnino je pa prepozno za kupon",
    "author": "perssak",
    "author_level": "Pripravnik"
  },
  {
    "ctx": "P:Kupon za brezplačno priključnino Tušmobil",
    "content": "Kuponi so še vedno na voljo.",
    "author": "tado",
    "author_level": "Fizikalc"
  },
  {
    "ctx": "P:Kupon za brezplačno priključnino Tušmobil",
    "content": "Zdaj mi nekaj ni jasno... A je pri koriščenju tega kupona potrebna vezava (kot piše v prvem postu) ali ne (kot piše v tvojem podpisu)?\n\nLP",
    "author": "Jst10",
    "author_level": "Pripravnik"
  },
  {
    "ctx": "P:Kupon za brezplačno priključnino Tušmobil",
    "content": "Vezava ni potrebna. LP",
    "author": "tado",
    "author_level": "Fizikalc"
  },
  {
    "ctx": "P:Kupon za brezplačno priključnino Tušmobil",
    "content": "Kaj pa kupon za priključnino na paket najbližji 1500 se da dobit ;-)\nLp",
    "author": "Jerym",
    "author_level": "Zelenc'"
  }
]