[
  {
    "ctx": "Google račun na 2 napravah hkrati",
    "content": "Trenutno imam Samsung Galaxy S4 in kar nekaj kupljenih aplikacij in iger.\n\nImenik oseb imam shranjen v gmail accountu in vedno aktivno sinhronizacijo.\n\nSedaj pa vprašanja:\n\n1. Če si še dodatno nabavim eno Android tablico in se vpišem z enakim gmail računom, kot ga imam na S4, ali bom lahko hkrati na tablici in telefonu imel že plačane aplikacije in igre (v kolikor so seveda pisane tudi za tablico)?\n\n2. Ali bom lahko imel na tablici identičen imenik (slike oseb, naslovi oseb, več številk pri osebah), kot ga imam na S4?\n\n3. Če bom recimo na S4 nekoga dodal v imenik, ali se bo ta oseba v nekaj sekundah dodala tudi na tablico (v primeru, da imam sinhronizacijo vedno aktovno) in obratno?\n\n4. Ali so vse igre in programi, ki so narejeni za S4 - enako na voljo za tablice?\n\nTo je to za 1x hvala  \n\t\n\n\t\n\t\n\t\t\n\t\t\n\n\t\t\n\t\t\t\n\t\t\n\t\t\n\t\n\n\n\t\n\t\t\n\t",
    "author": "sylver",
    "author_level": "Fizikalc"
  },
  {
    "ctx": "Google račun na 2 napravah hkrati",
    "content": "Lahko imaš več naprav, aplikacije pa so potem na vseh enake. Podatki pa se načeloma tudi samodejno sinhronizirajo - odvisno od aplikacije do aplikacije. Pri kakih igrah se ti mogoče ne bodo odklenjeni leveli sinhronizirali, to pa je načeloma tudi to. Vse te business aplikacije (imenik, gmail ipd.) pa se kompletno sinhronizirajo. Imenik moraš seveda imeti na gmailu, lokalni imenik se seveda ne bo sinhroniziral z drugimi napravami.\n\nAplikacije pa normalno delajo tudi na tablicah. Nekatere aplikacije imajo prav za tablice prirejen uporabniški vmesnik, sicer pa pač zgleda enako, le da je pač večje.",
    "author": "philips",
    "author_level": "Guru"
  },
  {
    "ctx": "Google račun na 2 napravah hkrati",
    "content": "1. DA\n\n2. nisem 100% ampak verjetno DA\n\n3. nisem 100% ampak verjetno DA\n\n3. večinoma",
    "author": "Chief_Wiggum",
    "author_level": "Fizikalc"
  },
  {
    "ctx": "Google račun na 2 napravah hkrati",
    "content": "Aha ok super, hvala vama  \n\t\n\n\t\n\t\n\t\t\n\t\t\n\n\t\t\n\t\t\n\t\n\n\n\t\n\t\t\n\t",
    "author": "sylver",
    "author_level": "Fizikalc"
  }
]