[
  {
    "ctx": "modem in 2 ruterja",
    "content": "Pred kratkim sem zamenjal stari kabelski modem za novega (cisco telemach). Sedaj pa ne morem vec npr. iz racunalnika ki je prek 2 ruterjev dostopati v modem, vcasih sem na racunalniku prek ruterja 2, lahko dostopal tudi do ruterja 1 in modema, sedaj pa ne najdem pravega naslova.. kje lahko to poiscem? Ima morda kaj veze da je ta cisco modem ze sam po sebi tudi ruter? vseeno bi moral imeti dostop vsaj do ruterja 1?",
    "author": "shit",
    "author_level": "Zelenc'"
  },
  {
    "ctx": "modem in 2 ruterja",
    "content": "Odpri cmd in vpiši \"tracert 8.8.8.8\" ter enter. Če imaš res dva routerja ti bo drug zapis njegov IP",
    "author": "cat",
    "author_level": "Fizikalc"
  }
]