[
  {
    "ctx": "P: Samsung Note 8",
    "content": "LP\nProdam Note 8 kupljen pri Simobilu 28.2.2018 tako, da je še v garanciji. Nikoli odprt ali na servisu. S tovarniškim sistemom, ki še vedno in redno dobiva mesečne posodobitve. Telefon nepoškodovan in popolnoma delujoč. Vedno nošen v ovitku in z zaščito ekrana. Priložim tri rabljene ovitke: Smoked prozorni, Zizo bolt modri s zaponko za pas oziroma možnost pritrditve na vzglavnik v avtomobilu in Samsungov alkantara v sivi barvi. Priložim tudi dve novi ukrivljeni zaščitni stekli. In seveda kar je v bilo priloženo ob nakupu in je večinoma nedotakneno.\n\nCena 260€\nLokacija: Slovenske Konjice možnost tudi ob avtocest izvoz Tepanje\n041567179 po možnosti sms",
    "author": "Izy",
    "author_level": "Pripravnik"
  },
  {
    "ctx": "P: Samsung Note 8",
    "content": "kar dvomim da ima 3 leta garancije...",
    "author": "netko",
    "author_level": "Guru"
  },
  {
    "ctx": "P: Samsung Note 8",
    "content": "Hvala za opozorilo, popravljeno!",
    "author": "Izy",
    "author_level": "Pripravnik"
  }
]