[
  {
    "ctx": "Peugeot 5008",
    "content": "Pozdravljeni imam en problem. Mam peugeota 5008 letnik 2015 do zdej je delalo vse b.p.  ko mi je pa 4 dni nazaj crknala luč na avtu je zacel pa zajebavat. Avta z daljincem ne morem vec odklent ga moram ročno ko dam kontakt se sam še 1x odklene. In potem laufa zmede pa uro in datum. S tem da so ga prklopl na računalnik ni blo napak, kupla nov akumolato isto dela, zamenjala baterijo ne odklepa. Ce po 10 minutah pridem nazaj se odklene ce je pa več kot 1 ura od tega se pa z daljincem ne da več odklent. Kaj bi lahko bilo. Prosim pomoč",
    "author": "tarantellla",
    "author_level": "Zelenc'"
  },
  {
    "ctx": "Peugeot 5008",
    "content": "Najbrz je sel alternator oz. Usmernik na njem. Zato je tudi crknila luc. Preveri napetost, ko motor tece.\n\nlp",
    "author": "merdzo",
    "author_level": "Majstr"
  },
  {
    "ctx": "Peugeot 5008",
    "content": "Najprej poskusi zamenjano žarnico nadomestit z drugo.\n\nZa štart najnižji strošek.",
    "author": "vincent",
    "author_level": "Guru"
  }
]